{"notebooks":{"demo/symbolic_angles.jl":{"id":"demo/symbolic_angles.jl","hash":"JpzBm5So97XZGt5XoYnpzP9KEK0sOC5LjU1yIjdeCYQ","html_path":"demo/symbolic_angles.html","statefile_path":"demo/symbolic_angles.plutostate","notebookfile_path":"demo/symbolic_angles.jl","current_hash":"JpzBm5So97XZGt5XoYnpzP9KEK0sOC5LjU1yIjdeCYQ","desired_hash":"JpzBm5So97XZGt5XoYnpzP9KEK0sOC5LjU1yIjdeCYQ","frontmatter":{"title":"symbolic_angles"}}},"pluto_version":"0.19.29","julia_version":"1.9.2","format_version":"1","title":null,"description":null,"collections":null}